distance/__init__.py
distance/abstract_distance.py
distance/cosine_distance.py
distance/distribution.py
distance/jensen_shannon_distance.py
fitting_text_distance/__init__.py
fitting_text_distance/fitting_distance.py
fitting_text_distance/fitting_text_distance.py
fitting_text_distance/oracle_claim.py
fitting_text_distance/distance/__init__.py
fitting_text_distance/distance/abstract_distance.py
fitting_text_distance/distance/cosine_distance.py
fitting_text_distance/distance/distribution.py
fitting_text_distance/distance/jensen_shannon_distance.py
fitting_text_distance/fitting_vectorization/__init__.py
fitting_text_distance/fitting_vectorization/fitting_vectorization.py
fitting_text_distance/fitting_vectorization/vector_from_dict.py
fitting_text_distance/fitting_vectorization/vector_from_iterable.py
fitting_text_distance/fitting_vectorization/vectorization.py
fitting_text_distance/tools/__init__.py
fitting_text_distance/tools/matrix_operations.py
fitting_vectorization/__init__.py
fitting_vectorization/fitting_vectorization.py
fitting_vectorization/vector_from_dict.py
fitting_vectorization/vector_from_iterable.py
fitting_vectorization/vectorization.py
tests/__init__.py
tests/benchmark.py
tests/random_vectors_and_probabilities.py
tests/test_distribution.py
tests/test_fitting_distance.py
tests/test_fitting_text_distance.py
tests/test_fitting_vectorization.py
tests/test_jensen_shannon_distance.py
tests/test_matrix_operations.py
tests/test_vector_from_dict.py
tests/test_vector_from_iterable.py
tests/test_vectorization.py
tools/__init__.py
tools/matrix_operations.py
fitting_text_distance-0.0.7.dist-info/LICENSE
fitting_text_distance-0.0.7.dist-info/METADATA
fitting_text_distance-0.0.7.dist-info/WHEEL
fitting_text_distance-0.0.7.dist-info/top_level.txt
fitting_text_distance-0.0.7.dist-info/RECORD
